vhtml/core/generate_mhtml.py
vhtml/core/generate_standalone_html.py
vhtml/core/html_generator.py
vhtml/core/layout_analyzer.py
vhtml/core/ocr_engine.py
vhtml/core/pdf_processor.py
vhtml/main.py
vhtml/models/document_classifier.py
vhtml/templates/form_template.html
vhtml/templates/universal_template.html
vhtml/utils/image_utils.py
vhtml/utils/logging_utils.py
vhtml/utils/text_utils.py
vhtml-0.2.8.dist-info/METADATA
vhtml-0.2.8.dist-info/WHEEL
vhtml-0.2.8.dist-info/RECORD
