Metadata-Version: 2.3
Name: vhtml
Version: 0.2.8
Summary: vhtml (ang. Visual HyperText Markup Language) - Optical character recognition and HTML layout analysis library
Author: Tom Sapletta
Requires-Python: >=3.11,<4.0
Classifier: Programming Language :: Python :: 3
Classifier: Programming Language :: Python :: 3.11
Classifier: Programming Language :: Python :: 3.12
Classifier: Programming Language :: Python :: 3.13
Provides-Extra: dev
Requires-Dist: Jinja2 (>=3.1.2,<4.0.0)
Requires-Dist: Pillow (>=10.0.1,<11.0.0)
Requires-Dist: PyMuPDF (>=1.23.5,<2.0.0)
Requires-Dist: beautifulsoup4 (>=4.13.4,<5.0.0)
Requires-Dist: easyocr (>=1.7.0,<2.0.0)
Requires-Dist: langdetect (>=1.0.9,<2.0.0)
Requires-Dist: matplotlib (>=3.7.2,<4.0.0)
Requires-Dist: numpy (>=1.24.3,<2.0.0)
Requires-Dist: opencv-contrib-python (>=4.8.1,<5.0.0)
Requires-Dist: opencv-python (>=4.8.1,<5.0.0)
Requires-Dist: pandas (>=2.0.3,<3.0.0)
Requires-Dist: pdf2image (>=1.16.3,<2.0.0)
Requires-Dist: polyglot (>=16.7.4,<17.0.0)
Requires-Dist: pytesseract (>=0.3.10,<0.4.0)
Requires-Dist: requests (>=2.31.0,<3.0.0)
Requires-Dist: scikit-image (>=0.21.0,<0.22.0)
Requires-Dist: seaborn (>=0.12.2,<0.13.0)
Requires-Dist: spacy (>=3.6.1,<4.0.0)
Requires-Dist: textblob (>=0.17.1,<0.18.0)
Requires-Dist: tqdm (>=4.66.1,<5.0.0)
